common_regression_issues/__init__.py
common_regression_issues/_modidx.py
common_regression_issues/measurement_error.py
common_regression_issues/multicollinearity.py
common_regression_issues/model_helpers/__init__.py
common_regression_issues/model_helpers/fourier.py
common_regression_issues/model_helpers/spline_models.py
common_regression_issues/synthetic_data/__init__.py
common_regression_issues/synthetic_data/grouped_regression_data.py
common_regression_issues/synthetic_data/multicollinearity_datagen.py
common_regression_issues/synthetic_data/simple_regression_data.py
common_regression_issues/utils/__init__.py
common_regression_issues/utils/plotting.py
common_regression_issues-0.0.1.dist-info/LICENSE
common_regression_issues-0.0.1.dist-info/METADATA
common_regression_issues-0.0.1.dist-info/WHEEL
common_regression_issues-0.0.1.dist-info/entry_points.txt
common_regression_issues-0.0.1.dist-info/top_level.txt
common_regression_issues-0.0.1.dist-info/RECORD
